imapmirror-8.0.4.data/scripts/offlineimap.py
imapmirror-8.0.4.dist-info/licenses/COPYING
offlineimap/CustomConfig.py
offlineimap/__init__.py
offlineimap/accounts.py
offlineimap/error.py
offlineimap/globals.py
offlineimap/imaplibutil.py
offlineimap/imapserver.py
offlineimap/imaputil.py
offlineimap/init.py
offlineimap/localeval.py
offlineimap/mbnames.py
offlineimap/threadutil.py
offlineimap/folder/Base.py
offlineimap/folder/Gmail.py
offlineimap/folder/GmailMaildir.py
offlineimap/folder/IMAP.py
offlineimap/folder/LocalStatus.py
offlineimap/folder/LocalStatusSQLite.py
offlineimap/folder/Maildir.py
offlineimap/folder/UIDMaps.py
offlineimap/folder/__init__.py
offlineimap/repository/Base.py
offlineimap/repository/Gmail.py
offlineimap/repository/GmailMaildir.py
offlineimap/repository/IMAP.py
offlineimap/repository/LocalStatus.py
offlineimap/repository/Maildir.py
offlineimap/repository/__init__.py
offlineimap/ui/Curses.py
offlineimap/ui/Machine.py
offlineimap/ui/Noninteractive.py
offlineimap/ui/TTY.py
offlineimap/ui/UIBase.py
offlineimap/ui/__init__.py
offlineimap/ui/debuglock.py
offlineimap/utils/__init__.py
offlineimap/utils/const.py
offlineimap/utils/distro_utils.py
offlineimap/utils/stacktrace.py
imapmirror-8.0.4.dist-info/METADATA
imapmirror-8.0.4.dist-info/WHEEL
imapmirror-8.0.4.dist-info/top_level.txt
imapmirror-8.0.4.dist-info/RECORD
