Metadata-Version: 2.4
Name: imapmirror
Version: 8.0.4
Summary: Disconnected Universal IMAP Mail Synchronization/Reader Support
Home-page: https://github.com/IMAPMirror/imapmirror
Author: John Goerzen and contributors
License: GPLv2+
License-File: COPYING
Requires-Dist: distro
Requires-Dist: imaplib2>=3.5
Requires-Dist: rfc6555
Requires-Dist: gssapi[kerberos]
Requires-Dist: portalocker[cygwin]
Dynamic: author
Dynamic: description
Dynamic: home-page
Dynamic: license
Dynamic: license-file
Dynamic: requires-dist
Dynamic: summary
